mycalc/calculator.py
chocho-0.0.1.dist-info/LICENSE
chocho-0.0.1.dist-info/METADATA
chocho-0.0.1.dist-info/WHEEL
chocho-0.0.1.dist-info/top_level.txt
chocho-0.0.1.dist-info/RECORD
