Metadata-Version: 2.1
Name: chocho
Version: 0.0.1
Summary: nice calculator
Home-page: https://github.com/chochohyun/chocho.git
Download-URL: https://github.com/chochohyun/chocho.git
Author: chohyunju
Classifier: Programming Language :: Python :: 3
License-File: LICENSE
Requires-Dist: pandas
Requires-Dist: numpy
Requires-Dist: matplotlib
Requires-Dist: scipy
